{ "frames": [
   {
    "filename": "0",
    "frame": { "x": 0, "y": 0, "w": 34, "h": 54 },
    "rotated": false,
    "trimmed": true,
    "spriteSourceSize": { "x": 3, "y": 18, "w": 34, "h": 54 },
    "sourceSize": { "w": 40, "h": 85 },
    "duration": 1000
   },
   {
    "filename": "1",
    "frame": { "x": 36, "y": 0, "w": 34, "h": 52 },
    "rotated": false,
    "trimmed": true,
    "spriteSourceSize": { "x": 3, "y": 18, "w": 34, "h": 52 },
    "sourceSize": { "w": 40, "h": 85 },
    "duration": 100
   },
   {
    "filename": "2",
    "frame": { "x": 72, "y": 0, "w": 34, "h": 49 },
    "rotated": false,
    "trimmed": true,
    "spriteSourceSize": { "x": 3, "y": 18, "w": 34, "h": 49 },
    "sourceSize": { "w": 40, "h": 85 },
    "duration": 66
   },
   {
    "filename": "3",
    "frame": { "x": 72, "y": 51, "w": 34, "h": 43 },
    "rotated": false,
    "trimmed": true,
    "spriteSourceSize": { "x": 3, "y": 18, "w": 34, "h": 43 },
    "sourceSize": { "w": 40, "h": 85 },
    "duration": 33
   },
   {
    "filename": "4",
    "frame": { "x": 36, "y": 54, "w": 34, "h": 37 },
    "rotated": false,
    "trimmed": true,
    "spriteSourceSize": { "x": 3, "y": 18, "w": 34, "h": 37 },
    "sourceSize": { "w": 40, "h": 85 },
    "duration": 33
   },
   {
    "filename": "5",
    "frame": { "x": 0, "y": 56, "w": 34, "h": 31 },
    "rotated": false,
    "trimmed": true,
    "spriteSourceSize": { "x": 3, "y": 18, "w": 34, "h": 31 },
    "sourceSize": { "w": 40, "h": 85 },
    "duration": 33
   },
   {
    "filename": "6",
    "frame": { "x": 0, "y": 89, "w": 34, "h": 25 },
    "rotated": false,
    "trimmed": true,
    "spriteSourceSize": { "x": 3, "y": 18, "w": 34, "h": 25 },
    "sourceSize": { "w": 40, "h": 85 },
    "duration": 33
   },
   {
    "filename": "7",
    "frame": { "x": 36, "y": 93, "w": 34, "h": 19 },
    "rotated": false,
    "trimmed": true,
    "spriteSourceSize": { "x": 3, "y": 18, "w": 34, "h": 19 },
    "sourceSize": { "w": 40, "h": 85 },
    "duration": 33
   },
   {
    "filename": "8",
    "frame": { "x": 72, "y": 96, "w": 34, "h": 13 },
    "rotated": false,
    "trimmed": true,
    "spriteSourceSize": { "x": 3, "y": 18, "w": 34, "h": 13 },
    "sourceSize": { "w": 40, "h": 85 },
    "duration": 66
   },
   {
    "filename": "9",
    "frame": { "x": 72, "y": 111, "w": 34, "h": 7 },
    "rotated": false,
    "trimmed": true,
    "spriteSourceSize": { "x": 3, "y": 18, "w": 34, "h": 7 },
    "sourceSize": { "w": 40, "h": 85 },
    "duration": 100
   },
   {
    "filename": "10",
    "frame": { "x": 36, "y": 114, "w": 34, "h": 4 },
    "rotated": false,
    "trimmed": true,
    "spriteSourceSize": { "x": 3, "y": 18, "w": 34, "h": 4 },
    "sourceSize": { "w": 40, "h": 85 },
    "duration": 1000
   }
 ],
 "meta": {
  "app": "http://www.aseprite.org/",
  "version": "1.3.11-dev",
  "image": "jbdoor.png",
  "format": "RGBA8888",
  "size": { "w": 106, "h": 118 },
  "scale": "1",
  "frameTags": [
  ]
 }
}
